jcutil/__init__.py
jcutil/consul.py
jcutil/consul.pyi
jcutil/crypto.py
jcutil/crypto.pyi
jcutil/crypto_utils.py
jcutil/data.py
jcutil/data.pyi
jcutil/defines.py
jcutil/netio.py
jcutil/schedjob.py
jcutil/chalk/__init__.py
jcutil/chalk/__init__.pyi
jcutil/core/__init__.py
jcutil/core/jsonfy.py
jcutil/core/pdtools.py
jcutil/dba/__init__.py
jcutil/dba/sqls.py
jcutil/drivers/__init__.py
jcutil/drivers/db.py
jcutil/drivers/mongo.py
jcutil/drivers/mq.py
jcutil/drivers/redis.py
jcutil/server/__init__.py
jcutil/server/config.py
jcutil/server/envars.py
jcutil-2.1.4.dist-info/METADATA
jcutil-2.1.4.dist-info/WHEEL
jcutil-2.1.4.dist-info/licenses/LICENSE
jcutil-2.1.4.dist-info/RECORD
