Metadata-Version: 2.4
Name: jcutil
Version: 2.1.4
Summary: A tool chain for the web service
Author-email: "Jochen.he" <thjl@hotmail.com>
License: MIT
License-File: LICENSE
Requires-Python: >=3.8
Requires-Dist: aiofiles>=24.1.0
Requires-Dist: apscheduler
Requires-Dist: colorama
Requires-Dist: httpx>=0.24.0
Requires-Dist: jcramda>=1.0.6
Requires-Dist: joblib
Requires-Dist: motor
Requires-Dist: pandas
Requires-Dist: passlib
Requires-Dist: py-consul
Requires-Dist: pycryptodomex
Requires-Dist: pyhcl
Requires-Dist: pymongo
Requires-Dist: python-dotenv
Requires-Dist: pyyaml
Requires-Dist: redis
Requires-Dist: websockets>=10.0
